pytistory/__init__.py
pytistory/__main__.py
pytistory/app.py
pytistory/callback.py
pytistory/cli.py
pytistory/exceptions.py
pytistory/api/__init__.py
pytistory/api/base_api.py
pytistory/api/blog.py
pytistory/api/category.py
pytistory/api/comment.py
pytistory/api/guestbook.py
pytistory/api/post.py
pytistory-0.0.1.dev1.dist-info/DESCRIPTION.rst
pytistory-0.0.1.dev1.dist-info/METADATA
pytistory-0.0.1.dev1.dist-info/RECORD
pytistory-0.0.1.dev1.dist-info/WHEEL
pytistory-0.0.1.dev1.dist-info/metadata.json
pytistory-0.0.1.dev1.dist-info/top_level.txt
