Metadata-Version: 2.0
Name: pytistory
Version: 0.0.1.dev1
Summary: 티스토리 블로그 api client입니다.
Home-page: https://github.com/JeongUkJae/pytistory
Author: Jeong Ukjae
Author-email: jeongukjae@gmail.com
License: MIT
Keywords: tistory blogging
Platform: UNKNOWN
Classifier: Development Status :: 2 - Pre-Alpha
Classifier: Intended Audience :: End Users/Desktop
Classifier: Topic :: Internet :: WWW/HTTP :: Site Management
Classifier: License :: OSI Approved :: MIT License
Classifier: Programming Language :: Python
Classifier: Programming Language :: Python :: 3
Classifier: Programming Language :: Python :: 3.6
Classifier: Operating System :: OS Independent
Requires-Dist: flask
Requires-Dist: requests
